ivitools/__init__.py
ivitools/__main__.py
ivitools/download.py
ivitools/extract.py
ivitools/player.py
ivitools/scan.py
ivitools/touch.py
ivitools/ffmpeg/__init__.py
ivitools/ffmpeg/chunks.py
ivitools/ffmpeg/mac.chunk1
ivitools/ffmpeg/mac.chunk2
ivitools/ffmpeg/win.chunk1
ivitools/ffmpeg/win.chunk2
ivitools-1.0.0.dist-info/METADATA
ivitools-1.0.0.dist-info/WHEEL
ivitools-1.0.0.dist-info/entry_points.txt
ivitools-1.0.0.dist-info/top_level.txt
ivitools-1.0.0.dist-info/RECORD
