Metadata-Version: 2.1
Name: ivitools
Version: 1.0.0
Author: Nemo2011
License: GPLv3+
Keywords: bilibili
Classifier: License :: OSI Approved :: GNU General Public License v3 or later (GPLv3+)
Classifier: Programming Language :: Python :: 3.8
Classifier: Programming Language :: Python :: 3.9
Classifier: Programming Language :: Python :: 3.10
Classifier: Programming Language :: Python :: 3.11
Requires-Python: >=3.8
Requires-Dist: bilibili-api-python (>=14.0.0.b0)
Requires-Dist: colorama (>=0.4)
Requires-Dist: tqdm (>=4.0.0)
